iitkgp_erp_login/__init__.py
iitkgp_erp_login/endpoints.py
iitkgp_erp_login/erp.py
iitkgp_erp_login/erp_responses.py
iitkgp_erp_login/logger.py
iitkgp_erp_login/read_mail.py
iitkgp_erp_login/utils.py
iitkgp_erp_login-2.4.5.dist-info/licenses/LICENSE
iitkgp_erp_login-2.4.5.dist-info/METADATA
iitkgp_erp_login-2.4.5.dist-info/WHEEL
iitkgp_erp_login-2.4.5.dist-info/top_level.txt
iitkgp_erp_login-2.4.5.dist-info/RECORD
