Metadata-Version: 2.4
Name: iitkgp_erp_login
Version: 2.4.5
Summary: A package to automate login process in ERP for IIT-KGP
Author-email: Arpit Bhardwaj <proffapt@pm.me>
Project-URL: Homepage, https://github.com/proffapt/iitkgp-erp-login-pypi
Project-URL: Bug Tracker, https://github.com/proffapt/iitkgp-erp-login-pypi/issues
Classifier: Programming Language :: Python :: 3
Classifier: License :: OSI Approved :: MIT License
Classifier: Operating System :: OS Independent
Requires-Python: >=3.6
License-File: LICENSE
Requires-Dist: bs4
Requires-Dist: requests
Requires-Dist: google-auth
Requires-Dist: google-auth-oauthlib
Requires-Dist: google-auth-httplib2
Requires-Dist: google-api-python-client
Dynamic: license-file
